practice_turkish/__init__.py
practice_turkish/dictionaries/__init__.py
practice_turkish/dictionaries/csvdictionary.py
practice_turkish/dictionaries/dictionary.py
practice_turkish/dictionaries/parse.py
practice_turkish/dictionaries/telegram.py
practice_turkish/dictionaries/turkrutdictionary.py
practice_turkish/filepath.py
practice_turkish/languages/__init__.py
practice_turkish/languages/clipboard.py
practice_turkish/languages/englishinput.py
practice_turkish/languages/languages.py
practice_turkish/languages/russianinput.py
practice_turkish/languages/turkishinput.py
practice_turkish/languages/validator.py
practice_turkish/make_csv.py
practice_turkish/number.py
practice_turkish/practice.py
practice_turkish/to_telegram.py
practice_turkish/translation.py
practice_turkish-1.4.1.dist-info/LICENSE
practice_turkish-1.4.1.dist-info/METADATA
practice_turkish-1.4.1.dist-info/WHEEL
practice_turkish-1.4.1.dist-info/entry_points.txt
practice_turkish-1.4.1.dist-info/RECORD
