Metadata-Version: 2.1
Name: practice-turkish
Version: 1.4.1
Summary: A set of tools to practice your Turkish
Home-page: https://github.com/FadeevEgor/PracticeTurkish
License: MIT
Author: Egor Fadeev
Author-email: fadeevegor@yandex.ru
Requires-Python: >=3.10,<4.0
Classifier: License :: OSI Approved :: MIT License
Classifier: Programming Language :: Python :: 3
Classifier: Programming Language :: Python :: 3.10
Classifier: Programming Language :: Python :: 3.11
Requires-Dist: inquirerpy (>=0.3.4,<0.4.0)
Requires-Dist: prompt-toolkit (>=3.0.38,<4.0.0)
Requires-Dist: requests (>=2.28.2,<3.0.0)
Requires-Dist: rich (>=13.3.2,<14.0.0)
Requires-Dist: typer (>=0.7.0,<0.8.0)
Project-URL: Repository, https://github.com/FadeevEgor/PracticeTurkish
